<?xml version="1.0" encoding="utf-8" ?>
<dwsync>
<file name="tpl_ajax_search_header.php" server="access916539848.webspace-data.io//webzero/" local="133034589385178952" remote="133034626440000000" Dst="2" />
<file name="tpl_best_sellers.php" server="access916539848.webspace-data.io//webzero/" local="133034589385178952" remote="133034626440000000" Dst="2" />
<file name="tpl_brands.php" server="access916539848.webspace-data.io//webzero/" local="133034589385178952" remote="133034626440000000" Dst="2" />
<file name="tpl_categories.php" server="access916539848.webspace-data.io//webzero/" local="133034589385178952" remote="133034626440000000" Dst="2" />
<file name="tpl_document_categories.php" server="access916539848.webspace-data.io//webzero/" local="133034589385178952" remote="133034626450000000" Dst="2" />
<file name="tpl_ezpages.php" server="access916539848.webspace-data.io//webzero/" local="133034589385178952" remote="133034626450000000" Dst="2" />
<file name="tpl_featured.php" server="access916539848.webspace-data.io//webzero/" local="133034589385178952" remote="133034626450000000" Dst="2" />
<file name="tpl_information.php" server="access916539848.webspace-data.io//webzero/" local="133034589385178952" remote="133034626450000000" Dst="2" />
<file name="tpl_more_information.php" server="access916539848.webspace-data.io//webzero/" local="133034589385178952" remote="133034626460000000" Dst="2" />
<file name="tpl_order_history.php" server="access916539848.webspace-data.io//webzero/" local="133034589385178952" remote="133034626460000000" Dst="2" />
<file name="tpl_reviews_random.php" server="access916539848.webspace-data.io//webzero/" local="133034589385178952" remote="133034626460000000" Dst="2" />
<file name="tpl_search.php" server="access916539848.webspace-data.io//webzero/" local="133034589385178952" remote="133034626460000000" Dst="2" />
<file name="tpl_search_header.php" server="access916539848.webspace-data.io//webzero/" local="133034589385178952" remote="133034626470000000" Dst="2" />
<file name="tpl_shopping_cart.php" server="access916539848.webspace-data.io//webzero/" local="133034589385178952" remote="133034626470000000" Dst="2" />
<file name="tpl_specials.php" server="access916539848.webspace-data.io//webzero/" local="133034589385178952" remote="133034626470000000" Dst="2" />
<file name="tpl_whats_new.php" server="access916539848.webspace-data.io//webzero/" local="133034589385178952" remote="133034626470000000" Dst="2" />
</dwsync>